<?xml version="1.0" encoding="UTF-8"?>
<turtleShapes>
  <shape name="person lumberjack" rotatable="false" editableColorIndex="0">
    <polygon color="-1920102913" filled="true" marked="true">
      <point x="105" y="90"></point>
      <point x="120" y="195"></point>
      <point x="90" y="285"></point>
      <point x="105" y="300"></point>
      <point x="135" y="300"></point>
      <point x="150" y="225"></point>
      <point x="165" y="300"></point>
      <point x="195" y="300"></point>
      <point x="210" y="285"></point>
      <point x="180" y="195"></point>
      <point x="195" y="90"></point>
    </polygon>
    <polygon color="-684578305" filled="true" marked="false">
      <point x="60" y="196"></point>
      <point x="90" y="211"></point>
      <point x="114" y="155"></point>
      <point x="120" y="196"></point>
      <point x="180" y="196"></point>
      <point x="187" y="158"></point>
      <point x="210" y="211"></point>
      <point x="240" y="196"></point>
      <point x="195" y="91"></point>
      <point x="165" y="91"></point>
      <point x="150" y="106"></point>
      <point x="150" y="135"></point>
      <point x="135" y="91"></point>
      <point x="105" y="91"></point>
    </polygon>
    <circle x="110" y="5" marked="true" color="-1920102913" diameter="80" filled="true"></circle>
    <rectangle endX="172" startY="79" marked="true" color="-1920102913" endY="94" startX="127" filled="true"></rectangle>
    <polygon color="-1653716737" filled="true" marked="false">
      <point x="174" y="90"></point>
      <point x="181" y="90"></point>
      <point x="180" y="195"></point>
      <point x="165" y="195"></point>
    </polygon>
    <polygon color="878553599" filled="true" marked="false">
      <point x="180" y="195"></point>
      <point x="120" y="195"></point>
      <point x="90" y="285"></point>
      <point x="105" y="300"></point>
      <point x="135" y="300"></point>
      <point x="150" y="225"></point>
      <point x="165" y="300"></point>
      <point x="195" y="300"></point>
      <point x="210" y="285"></point>
    </polygon>
    <polygon color="-1653716737" filled="true" marked="false">
      <point x="126" y="90"></point>
      <point x="119" y="90"></point>
      <point x="120" y="195"></point>
      <point x="135" y="195"></point>
    </polygon>
    <rectangle endX="255" startY="180" marked="false" color="-1653716737" endY="195" startX="45" filled="true"></rectangle>
    <polygon color="255" filled="true" marked="false">
      <point x="255" y="165"></point>
      <point x="255" y="195"></point>
      <point x="240" y="225"></point>
      <point x="255" y="240"></point>
      <point x="285" y="240"></point>
      <point x="300" y="225"></point>
      <point x="285" y="195"></point>
      <point x="285" y="165"></point>
    </polygon>
    <line endX="165" startY="165" marked="false" color="255" endY="165" startX="135"></line>
    <line endX="165" startY="135" marked="false" color="255" endY="135" startX="135"></line>
    <line endX="120" startY="135" marked="false" color="255" endY="135" startX="90"></line>
    <line endX="120" startY="120" marked="false" color="255" endY="120" startX="105"></line>
    <line endX="195" startY="120" marked="false" color="255" endY="120" startX="180"></line>
    <line endX="210" startY="135" marked="false" color="255" endY="135" startX="180"></line>
    <line endX="105" startY="150" marked="false" color="255" endY="165" startX="90"></line>
    <line endX="210" startY="165" marked="false" color="255" endY="180" startX="225"></line>
    <line endX="90" startY="165" marked="false" color="255" endY="180" startX="75"></line>
    <line endX="195" startY="150" marked="false" color="255" endY="165" startX="210"></line>
    <line endX="210" startY="105" marked="false" color="255" endY="180" startX="180"></line>
    <line endX="90" startY="105" marked="false" color="255" endY="180" startX="120"></line>
    <line endX="150" startY="135" marked="false" color="255" endY="165" startX="150"></line>
    <polygon color="-684578305" filled="true" marked="false">
      <point x="100" y="30"></point>
      <point x="104" y="44"></point>
      <point x="189" y="24"></point>
      <point x="185" y="10"></point>
      <point x="173" y="10"></point>
      <point x="166" y="1"></point>
      <point x="138" y="-1"></point>
      <point x="111" y="3"></point>
      <point x="109" y="28"></point>
    </polygon>
  </shape>
</turtleShapes>
